r2connect/__init__.py
r2connect/r2client.py
r2connect/exceptions/__init__.py
r2connect/exceptions/cloudflare/__init__.py
r2connect/exceptions/cloudflare/r2.py
r2connect/utils/__init__.py
r2connect/utils/files/__init__.py
r2connect/utils/files/filepath.py
tests/__init__.py
tests/unit/__init__.py
tests/unit/test_buckets.py
tests/unit/test_files.py
r2connect-1.1.2.dist-info/LICENSE
r2connect-1.1.2.dist-info/METADATA
r2connect-1.1.2.dist-info/WHEEL
r2connect-1.1.2.dist-info/top_level.txt
r2connect-1.1.2.dist-info/RECORD
