Metadata-Version: 2.1
Name: r2connect
Version: 1.1.2
Summary: R2Connect is a powerful Python module designed for seamless integration between AWS S3 and Cloudflare's R2 service. It offers a simple and intuitive interface to create, manage, and synchronize buckets, objects, and data, facilitating efficient backend operations in a reliable and secure manner. Streamline your S3 and R2 interactions with R2Connect.
Home-page: https://github.com/mo-awais/r2connect
Author: Mohammed Awais
Author-email: awais@mohammedawais.me
Classifier: Programming Language :: Python :: 3.11
Classifier: License :: OSI Approved :: GNU Affero General Public License v3
License-File: LICENSE
Requires-Dist: boto3 (==1.28.63)
Requires-Dist: botocore (==1.31.63)
Requires-Dist: jmespath (==1.0.1)
Requires-Dist: python-dateutil (==2.8.2)
Requires-Dist: s3transfer (==0.7.0)
Requires-Dist: six (==1.16.0)
Requires-Dist: urllib3 (==2.0.7)
